followmail.py
followmail-1.1.0.dist-info/licenses/LICENSE.md
followmail-1.1.0.dist-info/METADATA
followmail-1.1.0.dist-info/WHEEL
followmail-1.1.0.dist-info/entry_points.txt
followmail-1.1.0.dist-info/top_level.txt
followmail-1.1.0.dist-info/RECORD
