Metadata-Version: 2.4
Name: followmail
Version: 1.1.0
Summary: Postfix log parser to follow a mail address.
Author-email: Matteo Guadrini <matteo.guadrini@hotmail.it>
Maintainer-email: Matteo Guadrini <matteo.guadrini@hotmail.it>
Project-URL: homepage, https://github.com/MatteoGuadrini/followmail
Project-URL: documentation, https://matteoguadrini.github.io/followmail/
Project-URL: changelog, https://github.com/MatteoGuadrini/followmail/blob/main/CHANGES.md
Classifier: Programming Language :: Python :: 3
Classifier: License :: OSI Approved :: GNU General Public License v3 (GPLv3)
Classifier: Operating System :: POSIX :: Linux
Requires-Python: >=3.7
License-File: LICENSE.md
Requires-Dist: tablib
Dynamic: license-file
